{
  "project_info": {
    "project_number": "616346397607",
    "project_id": "zuralog-8311a",
    "storage_bucket": "zuralog-8311a.firebasestorage.app"
  },
  "client": [
    {
      "client_info": {
        "mobilesdk_app_id": "1:616346397607:android:1c1ba3c10ad227fe8c6482",
        "android_client_info": {
          "package_name": "com.zuralog.zuralog"
        }
      },
      "oauth_client": [
        {
          "client_id": "616346397607-se60r20r85d24teksi3oco8ss77kol0d.apps.googleusercontent.com",
          "client_type": 3
        }
      ],
      "api_key": [
        {
          "current_key": "AIzaSyBkKsmA2R4qF5ImOIw59iD4OhAsR_Sma1w"
        }
      ],
      "services": {
        "appinvite_service": {
          "other_platform_oauth_client": [
            {
              "client_id": "616346397607-se60r20r85d24teksi3oco8ss77kol0d.apps.googleusercontent.com",
              "client_type": 3
            },
            {
              "client_id": "616346397607-virjdumer2q771env27qjajjhmqtsia2.apps.googleusercontent.com",
              "client_type": 2,
              "ios_info": {
                "bundle_id": "com.zuralog.zuralog"
              }
            }
          ]
        }
      }
    }
  ],
  "configuration_version": "1"
}